setup.py
json_rpc_helpers.egg-info/PKG-INFO
json_rpc_helpers.egg-info/SOURCES.txt
json_rpc_helpers.egg-info/dependency_links.txt
json_rpc_helpers.egg-info/requires.txt
json_rpc_helpers.egg-info/top_level.txt
jsonrpc_helpers/__init__.py
jsonrpc_helpers/log.py
jsonrpc_helpers/validation.py
jsonrpc_helpers/tests/__init__.py
jsonrpc_helpers/tests/test_log.py
jsonrpc_helpers/tests/test_validation.py