Metadata-Version: 1.1
Name: json-rpc-helpers
Version: 1.0.0
Summary: Helpers for bootstrapping of JSON-RPC API
Home-page: https://github.com/lorehov/json-rpc-helpers
Author: Lev Orekhov
Author-email: lev.orekhov@gmail.com
License: MIT
Keywords: json-rpc json-schema validation logging
Platform: UNKNOWN
Classifier: Development Status :: 5 - Production/Stable
Classifier: Environment :: Console
Classifier: License :: OSI Approved :: MIT License
Classifier: Natural Language :: English
Classifier: Operating System :: OS Independent
Classifier: Programming Language :: Python :: 2.7
Classifier: Programming Language :: Python :: 3.4
Classifier: Topic :: Software Development :: Libraries :: Python Modules
